seq100111_detector.v
module seq100111_detector(input clk, input reset, input din, output reg detected);

  // State encoding
  parameter S0 = 3'd0;
  parameter S1 = 3'd1;
  parameter S2 = 3'd2;
  parameter S3 = 3'd3;
  parameter S4 = 3'd4;
  parameter S5 = 3'd5;
  parameter S6 = 3'd6;

  reg [2:0] state, next_state;

  always @(posedge clk or posedge reset) begin
    if (reset)
      state <= S0;
    else
      state <= next_state;
  end

  always @(*) begin
    detected = 0;
    case (state)
      S0: begin
        if (din == 1'b0) next_state = S0;
        if (din == 1'b1) next_state = S1;
      end
      S1: begin
        if (din == 1'b0) next_state = S2;
        if (din == 1'b1) next_state = S1;
      end
      S2: begin
        if (din == 1'b0) next_state = S3;
        if (din == 1'b1) next_state = S1;
      end
      S3: begin
        if (din == 1'b0) next_state = S0;
        if (din == 1'b1) next_state = S4;
      end
      S4: begin
        if (din == 1'b0) next_state = S2;
        if (din == 1'b1) next_state = S5;
      end
      S5: begin
        if (din == 1'b0) next_state = S2;
        if (din == 1'b1) next_state = S6;
      end
      S6: begin
        detected = 1;
        if (din == 1'b0) next_state = S2;
        if (din == 1'b1) next_state = S1;
      end
      default: next_state = S0;
    endcase
  end
endmodule

seq100111_detector_tb.v
module tb_seq100111;
  reg clk, reset, din;
  wire detected;
  seq100111_detector uut (.clk(clk), .reset(reset), .din(din), .detected(detected));

  initial begin
    clk = 0;
    forever #5 clk = ~clk;
  end

  initial begin
    $dumpfile("wave.vcd");
    $dumpvars(0, uut);
    reset = 1; din = 0; #12;
    reset = 0;
    // Test stream: 100111001111001011110011110011100111
    din = 1'b1; #10;
    din = 1'b0; #10;
    din = 1'b0; #10;
    din = 1'b1; #10;
    din = 1'b1; #10;
    din = 1'b1; #10;
    din = 1'b0; #10;
    din = 1'b0; #10;
    din = 1'b1; #10;
    din = 1'b1; #10;
    din = 1'b1; #10;
    din = 1'b1; #10;
    din = 1'b0; #10;
    din = 1'b0; #10;
    din = 1'b1; #10;
    din = 1'b0; #10;
    din = 1'b1; #10;
    din = 1'b1; #10;
    din = 1'b1; #10;
    din = 1'b1; #10;
    din = 1'b0; #10;
    din = 1'b0; #10;
    din = 1'b1; #10;
    din = 1'b1; #10;
    din = 1'b1; #10;
    din = 1'b1; #10;
    din = 1'b0; #10;
    din = 1'b0; #10;
    din = 1'b1; #10;
    din = 1'b1; #10;
    din = 1'b1; #10;
    din = 1'b0; #10;
    din = 1'b0; #10;
    din = 1'b1; #10;
    din = 1'b1; #10;
    din = 1'b1; #10;
    #20; $finish;
  end
endmodule

wave.vcd
$date
	Sun Aug 31 22:23:04 2025
$end
$version
	Icarus Verilog
$end
$timescale
	1s
$end
$scope module tb_seq100111 $end
$scope module uut $end
$var wire 1 ! clk $end
$var wire 1 " din $end
$var wire 1 # reset $end
$var parameter 3 $ S0 $end
$var parameter 3 % S1 $end
$var parameter 3 & S2 $end
$var parameter 3 ' S3 $end
$var parameter 3 ( S4 $end
$var parameter 3 ) S5 $end
$var parameter 3 * S6 $end
$var reg 1 + detected $end
$var reg 3 , next_state [2:0] $end
$var reg 3 - state [2:0] $end
$upscope $end
$upscope $end
$enddefinitions $end
$comment Show the parameter values. $end
$dumpall
b110 *
b101 )
b100 (
b11 '
b10 &
b1 %
b0 $
$end
#0
$dumpvars
b0 -
b0 ,
0+
1#
0"
0!
$end
#5
1!
#10
0!
#12
b1 ,
1"
0#
#15
b1 -
1!
#20
0!
#22
b10 ,
0"
#25
b11 ,
b10 -
1!
#30
0!
#35
b0 ,
b11 -
1!
#40
0!
#42
b100 ,
1"
#45
b101 ,
b100 -
1!
#50
0!
#55
b110 ,
b101 -
1!
#60
0!
#65
b1 ,
1+
b110 -
1!
#70
0!
#72
b10 ,
1+
0"
#75
b11 ,
0+
b10 -
1!
#80
0!
#85
b0 ,
b11 -
1!
#90
0!
#92
b100 ,
1"
#95
b101 ,
b100 -
1!
#100
0!
#105
b110 ,
b101 -
1!
#110
0!
#115
b1 ,
1+
b110 -
1!
#120
0!
#125
0+
b1 -
1!
#130
0!
#132
b10 ,
0"
#135
b11 ,
b10 -
1!
#140
0!
#145
b0 ,
b11 -
1!
#150
0!
#152
b100 ,
1"
#155
b101 ,
b100 -
1!
#160
0!
#162
b10 ,
0"
#165
b11 ,
b10 -
1!
#170
0!
#172
b1 ,
1"
#175
b1 -
1!
#180
0!
#185
1!
#190
0!
#195
1!
#200
0!
#205
1!
#210
0!
#212
b10 ,
0"
#215
b11 ,
b10 -
1!
#220
0!
#225
b0 ,
b11 -
1!
#230
0!
#232
b100 ,
1"
#235
b101 ,
b100 -
1!
#240
0!
#245
b110 ,
b101 -
1!
#250
0!
#255
b1 ,
1+
b110 -
1!
#260
0!
#265
0+
b1 -
1!
#270
0!
#272
b10 ,
0"
#275
b11 ,
b10 -
1!
#280
0!
#285
b0 ,
b11 -
1!
#290
0!
#292
b100 ,
1"
#295
b101 ,
b100 -
1!
#300
0!
#305
b110 ,
b101 -
1!
#310
0!
#315
b1 ,
1+
b110 -
1!
#320
0!
#322
b10 ,
1+
0"
#325
b11 ,
0+
b10 -
1!
#330
0!
#335
b0 ,
b11 -
1!
#340
0!
#342
b100 ,
1"
#345
b101 ,
b100 -
1!
#350
0!
#355
b110 ,
b101 -
1!
#360
0!
#365
b1 ,
1+
b110 -
1!
#370
0!
#375
0+
b1 -
1!
